simple_wifi_qrcode/__init__.py
simple_wifi_qrcode/__main__.py
simple_wifi_qrcode/qrcode.py
simple_wifi_qrcode/wifi.py
simple_wifi_qrcode-1.4.4.dist-info/LICENSE
simple_wifi_qrcode-1.4.4.dist-info/METADATA
simple_wifi_qrcode-1.4.4.dist-info/WHEEL
simple_wifi_qrcode-1.4.4.dist-info/entry_points.txt
simple_wifi_qrcode-1.4.4.dist-info/top_level.txt
simple_wifi_qrcode-1.4.4.dist-info/RECORD
