Metadata-Version: 2.1
Name: simple-wifi-qrcode
Version: 1.4.4
Summary: Generates a QRCode to join wifi networks by scanning it
Author-email: João Paulo Lobianco <joaopaulolobianco1@gmail.com>
License: MIT License
Project-URL: Homepage, https://github.com/jplobianco/simple-wifi-qrcode
Keywords: wifi,qrcode,scan
Classifier: License :: OSI Approved :: MIT License
Classifier: Programming Language :: Python
Classifier: Programming Language :: Python :: 3
Requires-Python: >=3.9
License-File: LICENSE
Requires-Dist: qrcode[pil] (>=7.3.1)
Provides-Extra: dev
Requires-Dist: black ; extra == 'dev'
Requires-Dist: bumpver ; extra == 'dev'
Requires-Dist: isort ; extra == 'dev'
Requires-Dist: pip-tools ; extra == 'dev'
Requires-Dist: pytest ; extra == 'dev'
Requires-Dist: pytest-cov ; extra == 'dev'
Requires-Dist: coverage ; extra == 'dev'
Requires-Dist: opencv-python ; extra == 'dev'
Requires-Dist: pre-commit ; extra == 'dev'
